Workbook

Sheet Dashboard
A1: HPO Idea Pipeline - Executive Summary
A3: Total Ideas Tracked | C3: =COUNTA(Ideas!A2:A51) -> 50
A4: Total Annual Savings Potential (INR Lakh) | C4: =SUM(Ideas!F2:F51) -> 5042
A5: Total Implementation Cost (INR Lakh) | C5: =SUM(Ideas!G2:G51) -> 1281
A6: Ideas Implemented (%) | C6: =COUNTIF(Ideas!N2:N51,"Implemented")/COUNTA(Ideas!A2:A51) -> 0.16
A7: Ideas In Progress / Approved (%) | C7: =(COUNTIF(Ideas!N2:N51,"In Progress")+COUNTIF(Ideas!N2:N51,"Approved"))/COUNTA(Ideas!A2:A51) -> 0.34
A8: Average Payback Period (Years) | C8: =AVERAGE(Ideas!H2:H51) -> 0.31619216
A10: Savings & Priority by Category
A11: Category | B11: Total Annual Savings (INR Lakh) | C11: # Ideas | D11: Avg Priority Score
A12: Digital & Automation | B12: =SUMIF(Ideas!$E$2:$E$51,A12,Ideas!$F$2:$F$51) -> 306 | C12: =COUNTIF(Ideas!$E$2:$E$51,A12) -> 5 | D12: =AVERAGEIF(Ideas!$E$2:$E$51,A12,Ideas!$M$2:$M$51) -> 3.01
A13: EV & Powertrain | B13: =SUMIF(Ideas!$E$2:$E$51,A13,Ideas!$F$2:$F$51) -> 783 | C13: =COUNTIF(Ideas!$E$2:$E$51,A13) -> 5 | D13: =AVERAGEIF(Ideas!$E$2:$E$51,A13,Ideas!$M$2:$M$51) -> 3.33
A14: Facilities & Energy | B14: =SUMIF(Ideas!$E$2:$E$51,A14,Ideas!$F$2:$F$51) -> 376 | C14: =COUNTIF(Ideas!$E$2:$E$51,A14) -> 5 | D14: =AVERAGEIF(Ideas!$E$2:$E$51,A14,Ideas!$M$2:$M$51) -> 2.88
A15: HR & Workforce | B15: =SUMIF(Ideas!$E$2:$E$51,A15,Ideas!$F$2:$F$51) -> 375 | C15: =COUNTIF(Ideas!$E$2:$E$51,A15) -> 5 | D15: =AVERAGEIF(Ideas!$E$2:$E$51,A15,Ideas!$M$2:$M$51) -> 3.15
A16: IT & Systems | B16: =SUMIF(Ideas!$E$2:$E$51,A16,Ideas!$F$2:$F$51) -> 168 | C16: =COUNTIF(Ideas!$E$2:$E$51,A16) -> 5 | D16: =AVERAGEIF(Ideas!$E$2:$E$51,A16,Ideas!$M$2:$M$51) -> 2.68
A17: Manufacturing & Production | B17: =SUMIF(Ideas!$E$2:$E$51,A17,Ideas!$F$2:$F$51) -> 612 | C17: =COUNTIF(Ideas!$E$2:$E$51,A17) -> 5 | D17: =AVERAGEIF(Ideas!$E$2:$E$51,A17,Ideas!$M$2:$M$51) -> 3.76
A18: Procurement & Vendor | B18: =SUMIF(Ideas!$E$2:$E$51,A18,Ideas!$F$2:$F$51) -> 1053 | C18: =COUNTIF(Ideas!$E$2:$E$51,A18) -> 5 | D18: =AVERAGEIF(Ideas!$E$2:$E$51,A18,Ideas!$M$2:$M$51) -> 3.98
A19: Quality & Warranty | B19: =SUMIF(Ideas!$E$2:$E$51,A19,Ideas!$F$2:$F$51) -> 412 | C19: =COUNTIF(Ideas!$E$2:$E$51,A19) -> 5 | D19: =AVERAGEIF(Ideas!$E$2:$E$51,A19,Ideas!$M$2:$M$51) -> 3.59
A20: Sales & Aftersales | B20: =SUMIF(Ideas!$E$2:$E$51,A20,Ideas!$F$2:$F$51) -> 359 | C20: =COUNTIF(Ideas!$E$2:$E$51,A20) -> 5 | D20: =AVERAGEIF(Ideas!$E$2:$E$51,A20,Ideas!$M$2:$M$51) -> 3.17
A21: Supply Chain & Logistics | B21: =SUMIF(Ideas!$E$2:$E$51,A21,Ideas!$F$2:$F$51) -> 598 | C21: =COUNTIF(Ideas!$E$2:$E$51,A21) -> 5 | D21: =AVERAGEIF(Ideas!$E$2:$E$51,A21,Ideas!$M$2:$M$51) -> 3.47
A23: Savings by Forecast Quarter (Approved + In Progress + Implemented)
A24: Quarter | B24: Total Annual Savings (INR Lakh)
A25: Q1 FY26 | B25: =SUMIF(Ideas!$O$2:$O$51,A25,Ideas!$F$2:$F$51) -> 810
A26: Q2 FY26 | B26: =SUMIF(Ideas!$O$2:$O$51,A26,Ideas!$F$2:$F$51) -> 1013
A27: Q3 FY26 | B27: =SUMIF(Ideas!$O$2:$O$51,A27,Ideas!$F$2:$F$51) -> 1655
A28: Q4 FY26 | B28: =SUMIF(Ideas!$O$2:$O$51,A28,Ideas!$F$2:$F$51) -> 1564

Sheet Assumptions
A1: Scoring Model - Weight Assumptions
A3: Savings Weight | B3: 0.4
A4: Payback Weight | B4: 0.25
A5: Ease of Implementation Weight | B5: 0.2
A6: Strategic Alignment Weight | B6: 0.15
A7: Total Weight (should equal 100%) | B7: =SUM(B3:B6) -> 1
A9: Savings Score Breakpoints (INR Lakh, Annual)
A10: Score 5: >= | B10: 300
A11: Score 4: >= | B11: 150
A12: Score 3: >= | B12: 75
A13: Score 2: >= | B13: 30
A14: Score 1: < | B14: 30
A16: Payback Score Breakpoints (Years)
A17: Score 5: <= | B17: 0.3
A18: Score 4: <= | B18: 0.6
A19: Score 3: <= | B19: 1
A20: Score 2: <= | B20: 2
A21: Score 1: > | B21: 2

Sheet Ideas
A1: Idea ID | B1: Idea Name | C1: Department | D1: Owner | E1: Category | F1: Annual Savings (INR Lakh) | G1: Implementation Cost (INR Lakh) | H1: Payback Period (Years) | I1: Ease Score (1-5) | J1: Alignment Score (1-5) | K1: Savings Score (1-5) | L1: Payback Score (1-5) | M1: Priority Score | N1: Status | O1: Forecast Quarter
A2: ID-001 | B2: Reduce paint shop rework rate via booth humidity control | C2: Production - Paint Shop | D2: R. Deshmukh | E2: Manufacturing & Production | F2: 145 | G2: 38 | H2: =G2/F2 -> 0.26206897 | I2: 3 | J2: 5 | K2: =IF(F2>=Assumptions!$B$10,5,IF(F2>=Assumptions!$B$11,4,IF(F2>=Assumptions!$B$12,3,IF(F2>=Assumptions!$B$13,2,1)))) -> 3 | L2: =IF(H2<=Assumptions!$B$17,5,IF(H2<=Assumptions!$B$18,4,IF(H2<=Assumptions!$B$19,3,IF(H2<=Assumptions!$B$20,2,1)))) -> 5 | M2: =(K2*Assumptions!$B$3)+(L2*Assumptions!$B$4)+(I2*Assumptions!$B$5)+(J2*Assumptions!$B$6) -> 3.8 | N2: In Progress | O2: Q2 FY26
A3: ID-002 | B3: Press shop die-change time reduction (SMED) | C3: Production - Press Shop | D3: A. Kulkarni | E3: Manufacturing & Production | F3: 210 | G3: 60 | H3: =G3/F3 -> 0.28571429 | I3: 2 | J3: 4 | K3: =IF(F3>=Assumptions!$B$10,5,IF(F3>=Assumptions!$B$11,4,IF(F3>=Assumptions!$B$12,3,IF(F3>=Assumptions!$B$13,2,1)))) -> 4 | L3: =IF(H3<=Assumptions!$B$17,5,IF(H3<=Assumptions!$B$18,4,IF(H3<=Assumptions!$B$19,3,IF(H3<=Assumptions!$B$20,2,1)))) -> 5 | M3: =(K3*Assumptions!$B$3)+(L3*Assumptions!$B$4)+(I3*Assumptions!$B$5)+(J3*Assumptions!$B$6) -> 3.85 | N3: Approved | O3: Q3 FY26
A4: ID-003 | B4: Line balancing optimization on Trim & Final assembly | C4: Production - TCF | D4: S. Iyer | E4: Manufacturing & Production | F4: 95 | G4: 15 | H4: =G4/F4 -> 0.15789474 | I4: 4 | J4: 4 | K4: =IF(F4>=Assumptions!$B$10,5,IF(F4>=Assumptions!$B$11,4,IF(F4>=Assumptions!$B$12,3,IF(F4>=Assumptions!$B$13,2,1)))) -> 3 | L4: =IF(H4<=Assumptions!$B$17,5,IF(H4<=Assumptions!$B$18,4,IF(H4<=Assumptions!$B$19,3,IF(H4<=Assumptions!$B$20,2,1)))) -> 5 | M4: =(K4*Assumptions!$B$3)+(L4*Assumptions!$B$4)+(I4*Assumptions!$B$5)+(J4*Assumptions!$B$6) -> 3.85 | N4: Implemented | O4: Q1 FY26
A5: ID-004 | B5: Reduce scrap rate in body shop welding cells | C5: Production - Body Shop | D5: M. Verma | E5: Manufacturing & Production | F5: 120 | G5: 25 | H5: =G5/F5 -> 0.20833333 | I5: 3 | J5: 5 | K5: =IF(F5>=Assumptions!$B$10,5,IF(F5>=Assumptions!$B$11,4,IF(F5>=Assumptions!$B$12,3,IF(F5>=Assumptions!$B$13,2,1)))) -> 3 | L5: =IF(H5<=Assumptions!$B$17,5,IF(H5<=Assumptions!$B$18,4,IF(H5<=Assumptions!$B$19,3,IF(H5<=Assumptions!$B$20,2,1)))) -> 5 | M5: =(K5*Assumptions!$B$3)+(L5*Assumptions!$B$4)+(I5*Assumptions!$B$5)+(J5*Assumptions!$B$6) -> 3.8 | N5: Under Review | O5: Q3 FY26
A6: ID-005 | B6: Compressed air leak audit and remediation across plant | C6: Production - Utilities | D6: P. Nair | E6: Manufacturing & Production | F6: 42 | G6: 8 | H6: =G6/F6 -> 0.19047619 | I6: 5 | J6: 3 | K6: =IF(F6>=Assumptions!$B$10,5,IF(F6>=Assumptions!$B$11,4,IF(F6>=Assumptions!$B$12,3,IF(F6>=Assumptions!$B$13,2,1)))) -> 2 | L6: =IF(H6<=Assumptions!$B$17,5,IF(H6<=Assumptions!$B$18,4,IF(H6<=Assumptions!$B$19,3,IF(H6<=Assumptions!$B$20,2,1)))) -> 5 | M6: =(K6*Assumptions!$B$3)+(L6*Assumptions!$B$4)+(I6*Assumptions!$B$5)+(J6*Assumptions!$B$6) -> 3.5 | N6: Implemented | O6: Q1 FY26
A7: ID-006 | B7: Milk-run inbound logistics for Tier-1 suppliers within 150km radius | C7: Supply Chain | D7: K. Reddy | E7: Supply Chain & Logistics | F7: 180 | G7: 45 | H7: =G7/F7 -> 0.25 | I7: 3 | J7: 4 | K7: =IF(F7>=Assumptions!$B$10,5,IF(F7>=Assumptions!$B$11,4,IF(F7>=Assumptions!$B$12,3,IF(F7>=Assumptions!$B$13,2,1)))) -> 4 | L7: =IF(H7<=Assumptions!$B$17,5,IF(H7<=Assumptions!$B$18,4,IF(H7<=Assumptions!$B$19,3,IF(H7<=Assumptions!$B$20,2,1)))) -> 5 | M7: =(K7*Assumptions!$B$3)+(L7*Assumptions!$B$4)+(I7*Assumptions!$B$5)+(J7*Assumptions!$B$6) -> 4.05 | N7: Approved | O7: Q2 FY26
A8: ID-007 | B8: Returnable packaging program to replace one-way cartons | C8: Supply Chain | D8: N. Joshi | E8: Supply Chain & Logistics | F8: 68 | G8: 20 | H8: =G8/F8 -> 0.29411765 | I8: 3 | J8: 3 | K8: =IF(F8>=Assumptions!$B$10,5,IF(F8>=Assumptions!$B$11,4,IF(F8>=Assumptions!$B$12,3,IF(F8>=Assumptions!$B$13,2,1)))) -> 2 | L8: =IF(H8<=Assumptions!$B$17,5,IF(H8<=Assumptions!$B$18,4,IF(H8<=Assumptions!$B$19,3,IF(H8<=Assumptions!$B$20,2,1)))) -> 5 | M8: =(K8*Assumptions!$B$3)+(L8*Assumptions!$B$4)+(I8*Assumptions!$B$5)+(J8*Assumptions!$B$6) -> 3.1 | N8: In Progress | O8: Q2 FY26
A9: ID-008 | B9: Warehouse slotting optimization for high-velocity SKUs | C9: Supply Chain | D9: D. Rao | E9: Supply Chain & Logistics | F9: 35 | G9: 6 | H9: =G9/F9 -> 0.17142857 | I9: 5 | J9: 2 | K9: =IF(F9>=Assumptions!$B$10,5,IF(F9>=Assumptions!$B$11,4,IF(F9>=Assumptions!$B$12,3,IF(F9>=Assumptions!$B$13,2,1)))) -> 2 | L9: =IF(H9<=Assumptions!$B$17,5,IF(H9<=Assumptions!$B$18,4,IF(H9<=Assumptions!$B$19,3,IF(H9<=Assumptions!$B$20,2,1)))) -> 5 | M9: =(K9*Assumptions!$B$3)+(L9*Assumptions!$B$4)+(I9*Assumptions!$B$5)+(J9*Assumptions!$B$6) -> 3.35 | N9: Implemented | O9: Q1 FY26
A10: ID-009 | B10: Consolidate CKD import shipments to reduce freight cost | C10: Supply Chain | D10: V. Menon | E10: Supply Chain & Logistics | F10: 260 | G10: 30 | H10: =G10/F10 -> 0.11538462 | I10: 3 | J10: 5 | K10: =IF(F10>=Assumptions!$B$10,5,IF(F10>=Assumptions!$B$11,4,IF(F10>=Assumptions!$B$12,3,IF(F10>=Assumptions!$B$13,2,1)))) -> 4 | L10: =IF(H10<=Assumptions!$B$17,5,IF(H10<=Assumptions!$B$18,4,IF(H10<=Assumptions!$B$19,3,IF(H10<=Assumptions!$B$20,2,1)))) -> 5 | M10: =(K10*Assumptions!$B$3)+(L10*Assumptions!$B$4)+(I10*Assumptions!$B$5)+(J10*Assumptions!$B$6) -> 4.2 | N10: Under Review | O10: Q4 FY26
A11: ID-010 | B11: Route optimization software for outbound vehicle carriers | C11: Supply Chain | D11: K. Reddy | E11: Supply Chain & Logistics | F11: 55 | G11: 22 | H11: =G11/F11 -> 0.4 | I11: 2 | J11: 3 | K11: =IF(F11>=Assumptions!$B$10,5,IF(F11>=Assumptions!$B$11,4,IF(F11>=Assumptions!$B$12,3,IF(F11>=Assumptions!$B$13,2,1)))) -> 2 | L11: =IF(H11<=Assumptions!$B$17,5,IF(H11<=Assumptions!$B$18,4,IF(H11<=Assumptions!$B$19,3,IF(H11<=Assumptions!$B$20,2,1)))) -> 4 | M11: =(K11*Assumptions!$B$3)+(L11*Assumptions!$B$4)+(I11*Assumptions!$B$5)+(J11*Assumptions!$B$6) -> 2.65 | N11: Idea | O11: Q4 FY26
A12: ID-011 | B12: Localize fasteners and rubber components currently imported | C12: Procurement | D12: S. Bhatt | E12: Procurement & Vendor | F12: 320 | G12: 55 | H12: =G12/F12 -> 0.171875 | I12: 2 | J12: 5 | K12: =IF(F12>=Assumptions!$B$10,5,IF(F12>=Assumptions!$B$11,4,IF(F12>=Assumptions!$B$12,3,IF(F12>=Assumptions!$B$13,2,1)))) -> 5 | L12: =IF(H12<=Assumptions!$B$17,5,IF(H12<=Assumptions!$B$18,4,IF(H12<=Assumptions!$B$19,3,IF(H12<=Assumptions!$B$20,2,1)))) -> 5 | M12: =(K12*Assumptions!$B$3)+(L12*Assumptions!$B$4)+(I12*Assumptions!$B$5)+(J12*Assumptions!$B$6) -> 4.4 | N12: Approved | O12: Q3 FY26
A13: ID-012 | B13: Vendor consolidation for indirect MRO spend | C13: Procurement | D13: T. Pillai | E13: Procurement & Vendor | F13: 88 | G13: 12 | H13: =G13/F13 -> 0.13636364 | I13: 4 | J13: 3 | K13: =IF(F13>=Assumptions!$B$10,5,IF(F13>=Assumptions!$B$11,4,IF(F13>=Assumptions!$B$12,3,IF(F13>=Assumptions!$B$13,2,1)))) -> 3 | L13: =IF(H13<=Assumptions!$B$17,5,IF(H13<=Assumptions!$B$18,4,IF(H13<=Assumptions!$B$19,3,IF(H13<=Assumptions!$B$20,2,1)))) -> 5 | M13: =(K13*Assumptions!$B$3)+(L13*Assumptions!$B$4)+(I13*Assumptions!$B$5)+(J13*Assumptions!$B$6) -> 3.7 | N13: In Progress | O13: Q2 FY26
... A51: ID-050 | B51: Predictive parts demand model to cut dealer overstock | C51: Aftersales | D51: N. Joshi | E51: Sales & Aftersales | F51: 46 | G51: 16 | H51: =G51/F51 -> 0.34782609 | I51: 3 | J51: 3 | K51: =IF(F51>=Assumptions!$B$10,5,IF(F51>=Assumptions!$B$11,4,IF(F51>=Assumptions!$B$12,3,IF(F51>=Assumptions!$B$13,2,1)))) -> 2 | L51: =IF(H51<=Assumptions!$B$17,5,IF(H51<=Assumptions!$B$18,4,IF(H51<=Assumptions!$B$19,3,IF(H51<=Assumptions!$B$20,2,1)))) -> 4 | M51: =(K51*Assumptions!$B$3)+(L51*Assumptions!$B$4)+(I51*Assumptions!$B$5)+(J51*Assumptions!$B$6) -> 2.85 | N51: Idea | O51: Q4 FY26
